{
  "context": {
    "city": "std:080",
    "action": "on_issue",
    "bap_id": "b-ondc-seller-bpp.nlincs.in",
    "bpp_id": "shipdh.in",
    "domain": "nic2004:60232",
    "bap_uri": "https://b-ondc-seller-bpp.nlincs.in/lbap",
    "bpp_uri": "https://shipdh.in/ondc/bpp/api/",
    "country": "IND",
    "timestamp": "2023-11-17T06:28:19.198Z",
    "message_id": "I24e8MhtCp9gburwUyiaD4Ar7R4w3WuQ",
    "core_version": "1.0.0",
    "transaction_id": "eec63e8f-59aa-41a4-a2cf-25e7ba70bac6"
  },
  "message": {
    "issue": {
      "id": "ReOGPkoVRQ96KXlDB50oRild",
      "created_at": "2023-11-17T05:54:01.638Z",
      "updated_at": "2023-11-17T05:57:35.612Z",
      "issue_actions": {
        "respondent_actions": [
          {
            "short_desc": "Complaint is being processed",
            "updated_at": "2023-11-17T05:54:52.160Z",
            "updated_by": {
              "org": {
                "name": "b-ondctsp.nlincs.in::nic2004:52110"
              },
              "person": {
                "name": "Sathish Kumar"
              },
              "contact": {
                "email": "sathisha@nstore.in",
                "phone": "9629295619"
              }
            },
            "cascaded_level": 1,
            "respondent_action": "PROCESSING"
          },
          {
            "short_desc": "Complaint cascaded",
            "updated_at": "2023-11-17T05:57:34.993Z",
            "updated_by": {
              "org": {
                "name": "b-ondc-seller-bpp.nlincs.in::nic2004:60232"
              },
              "person": {
                "name": "Sathish Kumar"
              },
              "contact": {
                "email": "sathisha@nstore.in",
                "phone": "9629295619"
              }
            },
            "cascaded_level": 2,
            "respondent_action": "CASCADED"
          },
          {
            "short_desc": "Complaint is being processed",
            "updated_at": "2023-11-17T05:57:35.612Z",
            "updated_by": {
              "org": {
                "name": "shipdh.in::nic2004:60232"
              },
              "person": {
                "name": "Pratham Sharma"
              },
              "contact": {
                "email": "pratham@shipdelight.com",
                "phone": "9875082482"
              }
            },
            "cascaded_level": 2,
            "respondent_action": "PROCESSING"
          }
        ]
      }
    }
  }
}
