{
    "context": {
        "domain": "ONDC:NTS10",
        "city": "*",
        "action": "on_receiver_recon",
        "core_version": "1.0.0",
        "bap_id": "api.razorpay.com",
        "bap_uri": "https://api.razorpay.com/rsp",
        "bpp_id": "preprod.ondc.adloggs.com",
        "bpp_uri": "https://preprod.ondc.adloggs.com/ondcapi",
        "transaction_id": "5fbdd03c-d54d-11ed-afa1-0242ad120025",
        "message_id": "54bd80f2-d849-11ed-870f-acde48001122",
        "timestamp": "2024-01-24T11:13:17.255Z",
        "ttl": "P2D"
    },
    "message": {
        "orderbook": {
            "orders": [{
                    "id": "922ca6d4-f0b9-4215-9647-28d219c17be1",
                    "invoice_no": "2023/XYZ/12346-3",
                    "collector_app_id": "preprod-ondc.addble.com",
                    "receiver_app_id": "preprod.ondc.adloggs.com",
                    "order_recon_status": "02",
                    "transaction_id": "0a14b693-33e2-4b14-b871-b6ee0ed701fd",
                    "settlement_id": "LcQnCmN9HUJl9J",
                    "settlement_reference_no": "LcQnCo6vNoHJMF",
                    "counterparty_recon_status": "03",
                    "message": {
                        "name": "",
                        "code": ""
                    }
                },
                {
                    "id": "59f36ae0-b720-4aa8-b910-f59d29f53f90",
                    "invoice_no": "2023/XYZ/12345-21",
                    "collector_app_id": "preprod-ondc.addble.com",
                    "receiver_app_id": "preprod.ondc.adloggs.com",
                    "order_recon_status": "02",
                    "transaction_id": "a71f9b5c-b12e-4408-8638-6ad6f1465d26",
                    "settlement_id": "LcQnCmOvqKTOea",
                    "settlement_reference_no": "LcQnCo72PIAPFp",
                    "counterparty_recon_status": "03",
                    "message": {
                        "name": "",
                        "code": ""
                    }
                }
            ]
        }
    }
}