{
    "context": {
        "ttl": "PT30S",
        "city": "std:044",
        "action": "on_init",
        "bap_id": "buyer-app-preprod.ondc.org",
        "bpp_id": "b-ondc-seller-bpp.nlincs.in",
        "domain": "nic2004:52110",
        "bap_uri": "https://buyer-app-preprod.ondc.org/protocol/v1",
        "bpp_uri": "https://b-ondc-seller-bpp.nlincs.in/bpp",
        "country": "IND",
        "timestamp": "2023-03-15T12:38:44.219Z",
        "message_id": "cbde8f6c-0ca6-48c2-85dd-96548faf5034",
        "core_version": "1.1.0",
        "transaction_id": "a724f979-bb52-4681-b2c7-d5a0e1b456c0"
    },
    "message": {
        "order": {
            "items": [
                {
                    "id": "135",
                    "quantity": {
                        "count": 7
                    },
                    "fulfillment_id": "20971"
                },
                {
                    "id": "224",
                    "quantity": {
                        "count": 5
                    },
                    "fulfillment_id": "20971"
                }
            ],
            "quote": {
                "ttl": "PT30M",
                "price": {
                    "value": "987.82",
                    "currency": "INR"
                },
                "breakup": [
                    {
                        "item": {
                            "price": {
                                "value": "101.00",
                                "currency": "INR"
                            }
                        },
                        "price": {
                            "value": "707.00",
                            "currency": "INR"
                        },
                        "title": "Maggi 2-Minute Masala Instant Noodles 560 g",
                        "@ondc/org/item_id": "135",
                        "@ondc/org/title_type": "item",
                        "@ondc/org/item_quantity": {
                            "count": 7
                        }
                    },
                    {
                        "price": {
                            "value": "0.00",
                            "currency": "INR"
                        },
                        "title": "Tax",
                        "@ondc/org/item_id": "135",
                        "@ondc/org/title_type": "tax"
                    },
                    {
                        "item": {
                            "price": {
                                "value": "51.00",
                                "currency": "INR"
                            }
                        },
                        "price": {
                            "value": "255.00",
                            "currency": "INR"
                        },
                        "title": "Maggi Masala Penne Instant Pazzta Family Saver Pack 130 g",
                        "@ondc/org/item_id": "224",
                        "@ondc/org/title_type": "item",
                        "@ondc/org/item_quantity": {
                            "count": 5
                        }
                    },
                    {
                        "price": {
                            "value": "0.00",
                            "currency": "INR"
                        },
                        "title": "Tax",
                        "@ondc/org/item_id": "224",
                        "@ondc/org/title_type": "tax"
                    },
                    {
                        "price": {
                            "value": "0.00",
                            "currency": "INR"
                        },
                        "title": "Delivery charges",
                        "@ondc/org/item_id": "20971",
                        "@ondc/org/title_type": "delivery"
                    },
                    {
                        "price": {
                            "value": "25.82",
                            "currency": "INR"
                        },
                        "title": "Convenience Fee",
                        "@ondc/org/item_id": "20971",
                        "@ondc/org/title_type": "misc"
                    }
                ]
            },
            "billing": {
                "name": "Santhosh",
                "email": "santhosh@nstore.in",
                "phone": "9551126655",
                "address": {
                    "city": "Chennai",
                    "name": "Santhosh",
                    "state": "Tamil Nadu",
                    "country": "IND",
                    "building": "nStore",
                    "locality": "No:105, 3rd Floor",
                    "area_code": "600028"
                },
                "created_at": "2023-03-15T12:38:39.092Z",
                "updated_at": "2023-03-15T12:38:39.092Z"
            },
            "payment": {
                "@ondc/org/settlement_details": [
                    {
                        "bank_name": "IDFC FIRST BANK LIMITED",
                        "branch_name": "BKC Naman Chambers Branch",
                        "settlement_type": "neft",
                        "beneficiary_name": "NSTORE TECHNOLOGIES PRIVATE LIMITED",
                        "settlement_phase": "sale-amount",
                        "settlement_ifsc_code": "IDFCB0040101",
                        "settlement_counterparty": "seller-app",
                        "settlement_bank_account_no": "10112822953"
                    }
                ],
                "@ondc/org/buyer_app_finder_fee_type": "percent",
                "@ondc/org/buyer_app_finder_fee_amount": "3.0"
            },
            "provider": {
                "id": "20971"
            },
            "fulfillments": [
                {
                    "id": "20971",
                    "end": {
                        "contact": {
                            "email": "santhosh@nstore.in",
                            "phone": "9551126655"
                        },
                        "location": {
                            "gps": "13.026197, 80.2656490000001",
                            "address": {
                                "city": "Chennai",
                                "name": "Santhosh",
                                "state": "Tamil Nadu",
                                "country": "IND",
                                "building": "nStore",
                                "locality": "No:105, 3rd Floor",
                                "area_code": "600028"
                            }
                        }
                    },
                    "type": "Delivery"
                }
            ],
            "provider_location": {
                "id": "20971"
            }
        }
    }
}