{
    "context": {
        "action": "update",
        "bap_id": "biz.test.enstore.com",
        "bap_uri": "https://biz.test.enstore.com/ecc/ondc/logistics-bap",
        "bpp_id": "ondc-wrapper-ondc.proxy.dev.dunzo.com",
        "bpp_uri": "https://ondc-wrapper-ondc.proxy.dev.dunzo.com/",
        "city": "std:080",
        "core_version": "1.1.0",
        "country": "IND",
        "domain": "nic2004:60232",
        "key": "",
        "message_id": "bd250807-c522-4b67-ae88-2e87846a2451",
        "timestamp": "2023-03-07T13:30:15.530Z",
        "transaction_id": "LOG-dfb5d937-cd87-48e6-8e62-1e7abc76cbf1",
        "ttl": "PT5S"
    },
    "message": {
        "order": {
            "fulfillments": [
                {
                    "id": "1",
                    "start": {
                        "instructions": {
                            "short_desc": "1003-1009"
                        }
                    },
                    "tags": {
                        "@ondc/org/order_ready_to_ship": "yes"
                    },
                    "type": "Prepaid"
                }
            ],
            "id": "2023-02-07-688480",
            "items": [
                {
                    "category_id": "Immediate Delivery",
                    "descriptor": {
                        "code": "P2P",
                        "long_desc": "Dunzo",
                        "name": "Dunzo",
                        "short_desc": "Dunzo"
                    },
                    "id": "item-3441a2f8-d442-454d-a776-6301adff1699"
                }
            ],
            "state": "Created"
        },
        "update_target": "fulfillment"
    }
}