{
    "context": {
        "bap_id": "integrations-preprod.channelier.com",
        "bap_uri": "https://integrations-preprod.channelier.com/ondc",
        "domain": "nic2004:60232",
        "core_version": "1.1.0",
        "ttl": "PT30S",
        "bpp_id": "ondc-dev.delhivery.com",
        "bpp_uri": "https://ondc-dev.delhivery.com/delhivery/v1/",
        "transaction_id": "f5074a23-a325-4a82-ba65-d2b1ddc6f314",
        "message_id": "a573eb97-04ea-40e6-b6d0-094e09d5a00f",
        "country": "IND",
        "city": "std:011",
        "timestamp": "2023-08-01T05:37:16.428Z",
        "action": "init"
    },
    "message": {
        "order": {
            "provider": {
                "id": "Delhivery"
            },
            "items": [
                {
                    "id": "b7b88f52-3da5-4ffd-b82c-a9fcd49adf6b",
                    "category_id": "Standard Delivery",
                    "descriptor": {
                        "code": "P2H2P"
                    }
                }
            ],
            "fulfillments": [
                {
                    "id": "1",
                    "type": "Prepaid",
                    "start": {
                        "location": {
                            "gps": "28.659569, 77.220845",
                            "address": {
                                "name": "Channelier Super Store",
                                "building": "Shopping Arcade",
                                "locality": "Tilak Bazaar",
                                "city": "Delhi",
                                "state": "DELHI",
                                "country": "India",
                                "area_code": "110006"
                            }
                        },
                        "contact": {
                            "phone": "9897989798",
                            "email": "techpvec18@gmail.com"
                        }
                    },
                    "end": {
                        "location": {
                            "gps": "28.561335, 77.349671",
                            "address": {
                                "building": "house no 16",
                                "name": "deepa",
                                "locality": "Sadarpur colony",
                                "city": "Gautam Buddh Nagar",
                                "state": "Uttar Pradesh",
                                "country": "India",
                                "area_code": "201303"
                            }
                        },
                        "contact": {
                            "phone": "6398356412"
                        }
                    }
                }
            ],
            "billing": {
                "name": "ONDC sellerapp",
                "address": {
                    "name": "My house or building no",
                    "building": "My house or building name",
                    "locality": "My street name",
                    "city": "Bengaluru",
                    "state": "Karnataka",
                    "country": "India",
                    "area_code": "560076"
                },
                "tax_number": "XXXXXXXXXXXXXXX",
                "phone": "9886098860",
                "email": "abcd.efgh@gmail.com",
                "created_at": "2023-08-01T05:37:16.428Z",
                "updated_at": "2023-08-01T05:37:16.428Z"
            }
        }
    }
}