{
    "context": {
        "domain": "nic2004:52110",
        "action": "on_issue_status",
        "core_version": "1.0.0",
        "bap_id": "buyer-app-preprod.ondc.org",
        "bap_uri": "https://buyer-app-preprod.ondc.org/protocol/v1",
        "transaction_id": "546b26ea-d057-4ed5-8df8-1f7afe3f4cc0",
        "message_id": "dab6e238-e2b9-4053-b4fc-79d671c10d11",
        "city": "std:080",
        "country": "IND",
        "timestamp": "2023-08-25T11:49:59.139Z",
        "bpp_id": "ondc-preprod.zeppstore.in",
        "bpp_uri": "https://ondc-preprod.zeppstore.in"
    },
    "message": {
        "issue": {
            "id": "2571a98c-d7ab-4236-906b-952205c41596",
            "issue_actions": {
                "respondent_actions": [
                    {
                        "respondent_action": "PROCESSING",
                        "short_desc": "Complaint is being processed",
                        "updated_at": "2023-08-25T11:35:24.033Z",
                        "updated_by": {
                            "org": {
                                "name": "ondc-preprod.zeppstore.in::ONDC:RET10"
                            },
                            "contact": {
                                "phone": "9606397001",
                                "email": "support@zrpl.co.in"
                            },
                            "person": {
                                "name": "Zeitgeist Retail Private Limited"
                            }
                        },
                        "cascaded_level": 1
                    }
                ]
            },
            "created_at": "2023-08-25T11:35:21.664Z",
            "updated_at": "2023-08-25T11:35:24.033Z"
        }
    }
}