{
    "context": {
        "domain": "nic2004:52110",
        "country": "IND",
        "city": "std:022",
        "action": "on_init",
        "core_version": "1.1.0",
        "bap_id": "buyer-app.ondc.org",
        "bap_uri": "https://buyer-app.ondc.org/protocol/v1",
        "bpp_uri": "https://api.lokal.in/ondc/",
        "transaction_id": "d38b8948-6458-45f0-8ba8-71635e808f8a",
        "message_id": "25ba06cf-854f-4ef6-b827-7d81281ff8bf",
        "timestamp": "2023-09-12T06:59:06.167Z",
        "bpp_id": "api.lokal.in",
        "ttl": "PT30S"
    },
    "message": {
        "order": {
            "provider": {
                "id": "OM Collection"
            },
            "items": [
                {
                    "fulfillment_id": "1",
                    "id": "490926",
                    "quantity": {
                        "count": 1
                    }
                }
            ],
            "billing": {
                "address": {
                    "door": "near",
                    "building": "near",
                    "city": "Mumbai",
                    "state": "Maharashtra",
                    "country": "IND",
                    "area_code": "400037",
                    "locality": "andheri",
                    "name": "sherin sha a j"
                },
                "phone": "9633432807",
                "name": "sherin sha a j",
                "email": "sherinsha.aj@xilligence.com",
                "created_at": "2023-09-12T06:59:04.807Z",
                "updated_at": "2023-09-12T06:59:04.807Z"
            },
            "fulfillments": [
                {
                    "id": "1",
                    "type": "Delivery",
                    "end": {
                        "contact": {
                            "email": "sherinsha.aj@xilligence.com",
                            "phone": "9633432807"
                        },
                        "location": {
                            "gps": "19.0179380000001, 72.863005",
                            "address": {
                                "name": "sherin sha a j",
                                "building": "near",
                                "locality": "andheri",
                                "city": "Mumbai",
                                "state": "Maharashtra",
                                "country": "IND",
                                "area_code": "400037"
                            }
                        }
                    }
                }
            ],
            "quote": {
                "price": {
                    "currency": "INR",
                    "value": "28.89"
                },
                "breakup": [
                    {
                        "@ondc/org/item_id": "490926",
                        "@ondc/org/item_quantity": {
                            "count": 1
                        },
                        "title": "Diet PopCorn",
                        "@ondc/org/title_type": "item",
                        "price": {
                            "currency": "INR",
                            "value": "28.05"
                        },
                        "item": {
                            "quantity": {
                                "available": {
                                    "count": 84
                                },
                                "maximum": {
                                    "count": 84
                                }
                            },
                            "price": {
                                "currency": "INR",
                                "value": "28.05"
                            }
                        }
                    },
                    {
                        "@ondc/org/item_id": "1",
                        "title": "Delivery charges",
                        "@ondc/org/title_type": "delivery",
                        "price": {
                            "currency": "INR",
                            "value": "0.00"
                        }
                    },
                    {
                        "@ondc/org/item_id": "1",
                        "title": "Convenience Fee",
                        "@ondc/org/title_type": "misc",
                        "price": {
                            "currency": "INR",
                            "value": "0.84"
                        }
                    }
                ],
                "ttl": "P1D"
            },
            "payment": {
                "@ondc/org/buyer_app_finder_fee_type": "percent",
                "@ondc/org/buyer_app_finder_fee_amount": "3.0",
                "@ondc/org/settlement_details": [
                    {
                        "settlement_counterparty": "seller-app",
                        "settlement_phase": "sale-amount",
                        "settlement_type": "neft",
                        "settlement_bank_account_no": "123456789087",
                        "settlement_ifsc_code": "SBIN0070074",
                        "settlement_timestamp": "2023-09-12T06:59:04.889Z",
                        "beneficiary_name": "Xilligence PRIVATE LIMITED",
                        "bank_name": "SBI",
                        "branch_name": "Andheri"
                    }
                ]
            },
            "provider_location": {
                "id": "OM Collection_lokal"
            }
        }
    }
}