{
    "context": {
        "domain": "nic2004:52110",
        "country": "IND",
        "city": "std:022",
        "action": "issue_status",
        "core_version": "1.0.0",
        "bap_id": "buyer-app-preprod.ondc.org",
        "bap_uri": "https://buyer-app-preprod.ondc.org/protocol/v1",
        "bpp_uri": "https://integrations-preprod.channelier.com/ondc",
        "transaction_id": "6f606549-b44e-4a80-b595-0e75db36b450",
        "message_id": "f8851eb8-a26a-46bd-8042-e67b926f49c1",
        "timestamp": "2023-06-22T11:44:21.561Z",
        "bpp_id": "integrations-preprod.channelier.com",
        "ttl": "PT30S"
    },
    "message": {
        "issue_id": "45f19259-de6a-45eb-afef-6e66b57aafee"
    }
}