{
    "message": {
        "order": {
            "fulfillments": [
                {
                    "tracking": true,
                    "end": {
                        "contact": {
                            "phone": "7007404190"
                        },
                        "location": {
                            "address": {
                                "building": "-",
                                "city": "Allahabad",
                                "door": "432 l/1 bairahana , prayagraj 211003",
                                "name": "432 l/1 bairahana , prayagraj 211003",
                                "locality": "432 l/1 bairahana , prayagraj 211003",
                                "country": "IN",
                                "area_code": "211003",
                                "state": "UTTAR PRADESH"
                            },
                            "gps": "25.4420088,81.8648413"
                        },
                        "time": {
                            "range": {
                                "start": "2023-03-10T18:16:19.000Z",
                                "end": "2023-03-13T18:16:19.000Z"
                            }
                        }
                    },
                    "@ondc/org/provider_name": "IDEAMASTERS SERVICES PRIVATE LIMITED",
                    "@ondc/org/category": "Standard Delivery",
                    "start": {
                        "contact": {
                            "phone": "9898458915",
                            "email": "bipindonda7566@gmail.com"
                        },
                        "location": {
                            "descriptor": {
                                "name": "175236"
                            },
                            "id": "175236",
                            "gps": "21.2135168,72.8861735"
                        },
                        "time": {
                            "range": {
                                "start": "2023-03-10T18:16:19.000Z",
                                "end": "2023-03-11T18:16:19.000Z"
                            }
                        }
                    },
                    "state": {
                        "descriptor": {
                            "code": "Cancelled"
                        }
                    },
                    "@ondc/org/TAT": "P4D",
                    "type": "Delivery",
                    "id": "1"
                }
            ],
            "billing": {
                "name": "SurajKesarwani",
                "created_at": "2023-03-10T12:46:02.296Z",
                "updated_at": "2023-03-10T12:46:02.296Z",
                "phone": "7007404190",
                "address": {
                    "building": "-",
                    "city": "Allahabad",
                    "door": "432 l/1 bairahana , prayagraj 211003",
                    "name": "432 l/1 bairahana , prayagraj 211003",
                    "locality": "432 l/1 bairahana , prayagraj 211003",
                    "country": "IN",
                    "area_code": "211003",
                    "state": "UTTAR PRADESH"
                },
                "tax_number": "",
                "email": "surajkesarwani2@gmail.com"
            },
            "items": [
                {
                    "fulfillment_id": "1",
                    "quantity": {
                        "count": 1
                    },
                    "id": "42835067",
                    "tags": {
                        "status": "Cancelled"
                    }
                },
                {
                    "fulfillment_id": "1",
                    "quantity": {
                        "count": 1
                    },
                    "id": "42835077",
                    "tags": {
                        "status": "Cancelled"
                    }
                }
            ],
            "created_at": "2023-03-10T12:46:19.000Z",
            "provider": {
                "rateable": true,
                "id": "175235",
                "locations": [
                    {
                        "id": "175236"
                    }
                ]
            },
            "updated_at": "2023-03-10T12:49:56.648Z",
            "payment": {
                "status": "PAID",
                "tl_method": "http/get",
                "collected_by": "BAP",
                "@ondc/org/settlement_details": [
                    {
                        "bank_name": "Kotak Mahindra Bank",
                        "beneficiary_name": "Ideamasters Services Private Limited",
                        "upi_address": "gft@oksbi",
                        "settlement_bank_account_no": "0846292065",
                        "settlement_ifsc_code": "KKBK0004256",
                        "settlement_timestamp": "",
                        "settlement_type": "neft",
                        "branch_name": "Sushant Lok-1 , Gurgaon. Haryana",
                        "settlement_counterparty": "seller-app",
                        "settlement_reference": "",
                        "settlement_phase": "sale-amount",
                        "settlement_status": "UN-PAID"
                    },
                    {
                        "settlement_timestamp": "2023-03-10T12:49:56.648Z",
                        "settlement_amount": "1098.00",
                        "settlement_counterparty": "buyer",
                        "settlement_type": "neft",
                        "settlement_phase": "refund"
                    }
                ],
                "uri": "ondc.indiastack.cloud/checkout",
                "params": {
                    "currency": "INR",
                    "amount": "1098.00",
                    "transaction_id": "order_LPpIKio22KAG52"
                },
                "@ondc/org/buyer_app_finder_fee_amount": "3",
                "type": "ON-ORDER",
                "@ondc/org/buyer_app_finder_fee_type": "percent"
            },
            "state": "Cancelled",
            "quote": {
                "breakup": [
                    {
                        "title": "DONDA CREATION 1 liter Plastic Food Grade Fridge Square Water Bottle Set Of 6 Multi-Color",
                        "price": {
                            "currency": "INR",
                            "value": "00.00"
                        },
                        "@ondc/org/title_type": "item",
                        "item": {
                            "price": {
                                "currency": "INR",
                                "value": "00.00"
                            }
                        },
                        "@ondc/org/item_quantity": {
                            "count": 1
                        },
                        "@ondc/org/item_id": "42835067"
                    },
                    {
                        "@ondc/org/item_id": "42835067",
                        "price": {
                            "currency": "INR",
                            "value": "00.00"
                        },
                        "@ondc/org/title_type": "tax",
                        "title": "Tax"
                    },
                    {
                        "@ondc/org/item_id": "42835067",
                        "price": {
                            "currency": "INR",
                            "value": "00.00"
                        },
                        "@ondc/org/title_type": "discount",
                        "title": "Discount"
                    },
                    {
                        "title": "DONDA CREATION 9 in1 chopper Vegetable & Fruit Grater Vegetable & Fruit Chopper Cutter",
                        "price": {
                            "currency": "INR",
                            "value": "00.00"
                        },
                        "@ondc/org/title_type": "item",
                        "item": {
                            "price": {
                                "currency": "INR",
                                "value": "00.00"
                            }
                        },
                        "@ondc/org/item_quantity": {
                            "count": 1
                        },
                        "@ondc/org/item_id": "42835077"
                    },
                    {
                        "@ondc/org/item_id": "42835077",
                        "price": {
                            "currency": "INR",
                            "value": "00.00"
                        },
                        "@ondc/org/title_type": "tax",
                        "title": "Tax"
                    },
                    {
                        "@ondc/org/item_id": "42835077",
                        "price": {
                            "currency": "INR",
                            "value": "00.00"
                        },
                        "@ondc/org/title_type": "discount",
                        "title": "Discount"
                    },
                    {
                        "@ondc/org/item_id": "1",
                        "price": {
                            "currency": "INR",
                            "value": "00.00"
                        },
                        "@ondc/org/title_type": "delivery",
                        "title": "Delivery charges"
                    },
                    {
                        "@ondc/org/item_id": "1",
                        "price": {
                            "currency": "INR",
                            "value": "00.00"
                        },
                        "@ondc/org/title_type": "misc",
                        "title": "Convenience Fee"
                    },
                    {
                        "@ondc/org/item_id": "1",
                        "price": {
                            "currency": "INR",
                            "value": "00.00"
                        },
                        "@ondc/org/title_type": "packing",
                        "title": "Packing charges"
                    }
                ],
                "price": {
                    "currency": "INR",
                    "value": "0.00"
                },
                "ttl": "P1D"
            },
            "id": "bee0fc42-d90a-40d2-b988-fe727b8b61fa"
        },
        "tags": {
            "cancellation_reason_id": "003"
        }
    },
    "context": {
        "city": "std:080",
        "domain": "nic2004:52110",
        "bpp_uri": "https://ondc.ideamasters.store/ondc/v1/166476/bpp",
        "core_version": "1.1.0",
        "timestamp": "2023-03-10T12:49:56.648Z",
        "bpp_id": "ondc.ideamasters.store",
        "bap_id": "ondc.indiastack.cloud",
        "action": "on_status",
        "bap_uri": "https://ondc.indiastack.cloud/ondc/v1/163525/",
        "country": "IND",
        "message_id": "4123202a-3a4d-4d74-baec-a1bda2e5b60c",
        "transaction_id": "be452d59-06f3-43a2-95df-86bf6a38a5fa"
    }
}