{
  "context": {
    "domain": "nic2004:52110",
    "country": "IND",
    "city": "std:080",
    "action": "init",
    "core_version": "1.1.0",
    "bap_id": "buyer-app-preprod.ondc.org",
    "bap_uri": "https://buyer-app-preprod.ondc.org/protocol/v1",
    "bpp_uri": "https://preprod-bpp.dbs.digiit.io",
    "transaction_id": "8d63f6aa-9cc7-417d-8862-9e460b5c2c92",
    "message_id": "9687ad63-903d-4d08-a58b-403c144e5f94",
    "timestamp": "2023-03-29T11:54:28.983Z",
    "bpp_id": "preprod-bpp.dbs.digiit.io",
    "ttl": "PT30S"
  },
  "message": {
    "order": {
      "provider": {
        "id": "171",
        "locations": [
          {
            "id": "384"
          }
        ]
      },
      "items": [
        {
          "id": "999",
          "quantity": {
            "count": 1
          },
          "fulfillment_id": "80853bb6-48dd-49de-ac6b-d1d649e800fe"
        },
        {
          "id": "1057",
          "quantity": {
            "count": 1
          },
          "fulfillment_id": "80853bb6-48dd-49de-ac6b-d1d649e800fe"
        }
      ],
      "billing": {
        "address": {
          "building": "Akshayanagar",
          "city": "Bengaluru",
          "state": "Karnataka",
          "country": "IND",
          "area_code": "560076",
          "locality": "Block-D, NANDI CITADEL, Akshaya Vana,",
          "name": "Clark Kent"
        },
        "phone": "9843123383",
        "name": "Clark Kent",
        "email": "clark@digiit.biz",
        "created_at": "2023-03-29T11:54:28.411Z",
        "updated_at": "2023-03-29T11:54:28.411Z"
      },
      "fulfillments": [
        {
          "id": "80853bb6-48dd-49de-ac6b-d1d649e800fe",
          "type": "Delivery",
          "end": {
            "contact": {
              "email": "clark@digiit.biz",
              "phone": "9843123383"
            },
            "location": {
              "gps": "12.898463, 77.600873",
              "address": {
                "name": "Clark Kent",
                "building": "Akshayanagar",
                "locality": "Block-D, NANDI CITADEL, Akshaya Vana,",
                "ward": null,
                "city": "Bengaluru",
                "state": "Karnataka",
                "country": "IND",
                "area_code": "560076"
              }
            }
          }
        }
      ]
    }
  }
}