{
  "context": {
    "domain": "nic2004:60232",
    "core_version": "1.1.0",
    "bap_id": "integrations-preprod.channelier.com",
    "bap_uri": "https://integrations-preprod.channelier.com/ondc",
    "bpp_id": "preprod-bpp.iway.digiit.io",
    "bpp_uri": "https://preprod-bpp.iway.digiit.io",
    "city": "std:080",
    "country": "IND",
    "action": "on_update",
    "transaction_id": "2bd5e6ee-892e-4814-b227-965136d55e2d",
    "message_id": "15a45ea8-5fd8-473d-8006-81550cc8ce6c",
    "timestamp": "2023-10-12T10:59:24.468Z"
  },
  "message": {
    "order": {
      "id": "ae02d660-5723-4187-a341-4b66b496ffc7",
      "state": "Accepted",
      "items": [
        {
          "id": "18",
          "category_id": "Next Day Delivery",
          "descriptor": {
            "code": "P2P"
          }
        }
      ],
      "fulfillments": [
        {
          "id": "1",
          "type": "Prepaid",
          "start": {
            "time": {
              "range": {
                "start": "2023-10-13T12:29:24.339Z",
                "end": "2023-10-13T12:59:24.339Z"
              }
            },
            "instructions": {
              "short_desc": "3858"
            }
          },
          "end": {
            "time": {
              "range": {
                "start": "2023-10-13T16:29:24.339Z",
                "end": "2023-10-13T16:44:24.339Z"
              }
            }
          },
          "agent": {
            "name": "Peter",
            "phone": "7438483828"
          }
        }
      ],
      "updated_at": "2023-10-12T10:59:24.468Z"
    }
  }
}