 {
    "context": {
      "key": "",
      "ttl": "PT5S",
      "city": "std:080",
      "action": "status",
      "bap_id": "biz.test.enstore.com",
      "bpp_id": "ondc-wrapper-ondc.proxy.dev.dunzo.com",
      "domain": "nic2004:60232",
      "bap_uri": "https://biz.test.enstore.com/ecc/ondc/logistics-bap",
      "bpp_uri": "https://ondc-wrapper-ondc.proxy.dev.dunzo.com/",
      "country": "IND",
      "timestamp": "2023-03-07T12:00:50.074Z",
      "message_id": "84ed8fd3-4e98-4d55-b924-c3895fd97844",
      "core_version": "1.1.0",
      "transaction_id": "LOG-493ae1b2-f95d-4103-aed5-a946b45a516e"
    },
    "message": {
      "order_id": "2023-02-07-215916"
    }
  }